releases1c/__init__.py
releases1c/__main__.py
releases1c/downloader.py
releases1c/error_codes.py
releases1c/manuals.py
releases1c/parsing.py
releases1c/progress.py
releases1c/request1c.py
releases1c/secrets.py
releases1c/shell_commands.py
releases1c-1.0.6.dist-info/LICENSE
releases1c-1.0.6.dist-info/METADATA
releases1c-1.0.6.dist-info/WHEEL
releases1c-1.0.6.dist-info/RECORD
